{
  "asOf": "2026-06-05",
  "bm20Level": 631.542286,
  "bm20PrevLevel": 654.66169,
  "bm20PointChange": -23.119404,
  "bm20ChangePct": -0.03531504,
  "returns": {
    "1D": -0.03531504,
    "7D": -0.11561173447462825,
    "30D": -0.1632102920092683,
    "1Y": -0.07437079498000765,
    "YTD": -0.03809679205253402
  },
  "kimchi": -0.025008,
  "kimchi_premium_pct": -2.5008,
  "kimchi_source": "/home/runner/work/bm/bm/out/2026-06-05/kimchi_2026-06-05.json",
  "kimchi_meta": {
    "usdkrw": 1532.6
  },
  "updatedAt": "2026-06-05T07:59:23+09:00"
}