{
  "schema": "smart_kimchi_v2",
  "timestamp_kst": "2026-06-09T17:29:32+0900",
  "timestamp_label": "06/09 17:29 KST",
  "prices": {
    "upbit": {
      "KRW-BTC": 94071000.0,
      "KRW-ETH": 2508000.0,
      "KRW-XRP": 1744.0,
      "KRW-USDT": 1495.0
    },
    "binance": {
      "BTCUSDT": 62890.97,
      "ETHUSDT": 1675.55,
      "XRPUSDT": 1.1674
    },
    "fx": {
      "USDKRW": 1520.56,
      "source": "yahoo_finance_direct"
    }
  },
  "kimchi_premium_pct": {
    "BTC": -1.63,
    "ETH": -1.561,
    "XRP": -1.752
  },
  "cb_premium_pct": -0.046,
  "kimchi_delta_pp": {
    "BTC": -0.041,
    "ETH": -0.01,
    "XRP": -0.11
  },
  "driver_share_pct": {
    "BTC": 25.3,
    "ETH": 6.3,
    "XRP": 68.4
  },
  "diagnostics": {
    "local_usdt_premium_hint_pct": -1.681
  },
  "smart_kimchi": {
    "type": "Reverse/Outflow",
    "rationale": "역김프 구간 → 해외가 더 비싸거나 국내 매수 약함/해외 이동 가능성",
    "score_v1": 56.8,
    "inputs": {
      "total_krw_24h": 2590501047366.03,
      "top10_share_pct": 65.2777339381877,
      "stable_dominance_pct": 8.923672443103271
    }
  }
}