{
  "schema": "smart_kimchi_v2",
  "timestamp_kst": "2026-07-18T14:34:26+0900",
  "timestamp_label": "07/18 14:34 KST",
  "prices": {
    "upbit": {
      "KRW-BTC": 94422000.0,
      "KRW-ETH": 2729000.0,
      "KRW-XRP": 1607.0,
      "KRW-USDT": 1478.0
    },
    "binance": {
      "BTCUSDT": 63981.99,
      "ETHUSDT": 1846.29,
      "XRPUSDT": 1.0893
    },
    "fx": {
      "USDKRW": 1487.46,
      "source": "yahoo_finance_direct"
    }
  },
  "kimchi_premium_pct": {
    "BTC": -0.787,
    "ETH": -0.629,
    "XRP": -0.82
  },
  "cb_premium_pct": -0.075,
  "kimchi_delta_pp": {
    "BTC": 0.008,
    "ETH": 0.188,
    "XRP": 0.037
  },
  "driver_share_pct": {
    "BTC": 3.6,
    "ETH": 80.6,
    "XRP": 15.8
  },
  "diagnostics": {
    "local_usdt_premium_hint_pct": -0.636
  },
  "smart_kimchi": {
    "type": "Neutral",
    "rationale": "뚜렷한 과열/제약 신호가 약함",
    "score_v1": 31.3,
    "inputs": {
      "total_krw_24h": 1221176538267.8708,
      "top10_share_pct": 48.38859504957821,
      "stable_dominance_pct": 7.724917297157745
    }
  }
}