{
  "schema": "smart_kimchi_v1",
  "timestamp_kst": "2026-01-27T15:58:26+0900",
  "timestamp_label": "01/27 15:58 KST",
  "prices": {
    "upbit": {
      "KRW-BTC": 129131000.0,
      "KRW-ETH": 4280000.0,
      "KRW-USDT": 1463.0
    },
    "binance": {
      "BTCUSDT": 88323.52,
      "ETHUSDT": 2929.0
    }
  },
  "kimchi_premium_pct": {
    "BTC": -0.067,
    "ETH": -0.12,
    "COMBO": -0.083
  },
  "smart_kimchi": {
    "type": "Neutral",
    "rationale": "뚜렷한 과열/제약 신호가 약함",
    "score_v1": 59.6,
    "inputs": {
      "total_krw_24h": 3445984390316.4565,
      "top10_share_pct": 57.01788927940381,
      "stable_dominance_pct": 10.618933713307356
    }
  }
}