{
  "schema": "krw_rolling24h_v1",
  "timestamp_kst": "2026-03-11T04:48:01+0900",
  "timestamp_label": "03/11 04:48 KST",
  "totals": {
    "combined_24h": 2745044471355.9873,
    "upbit_24h": 1790335706247.7146,
    "bithumb_24h": 762603148233.5693,
    "coinone_24h": 192105616874.70538
  },
  "stablecoins": {
    "total_stable_vol_24h": 379885338157.26624,
    "stable_dominance_pct": 13.83895022908725,
    "by_asset": {
      "USDC": 105366822065.08856,
      "USDT": 274518516092.17767
    }
  },
  "by_exchange_top": {
    "upbit_top5": [
      {
        "symbol": "KRW-XRP",
        "value": 324314649611.3335
      },
      {
        "symbol": "KRW-BTC",
        "value": 212109478243.2213
      },
      {
        "symbol": "KRW-ETH",
        "value": 132037014904.89816
      },
      {
        "symbol": "KRW-FLOW",
        "value": 115881167656.82117
      },
      {
        "symbol": "KRW-USDT",
        "value": 112566032521.10931
      }
    ],
    "bithumb_top5": [
      {
        "symbol": "KRW-XRP",
        "value": 130044588024.70114
      },
      {
        "symbol": "KRW-USDT",
        "value": 121775583091.13068
      },
      {
        "symbol": "KRW-BTC",
        "value": 90904894676.9525
      },
      {
        "symbol": "KRW-ETH",
        "value": 63566193374.33095
      },
      {
        "symbol": "KRW-DOGE",
        "value": 26258185904.09818
      }
    ],
    "coinone_top5": [
      {
        "symbol": "KRW-USDC",
        "value": 101436973011.545
      },
      {
        "symbol": "KRW-USDT",
        "value": 40176900479.9377
      },
      {
        "symbol": "KRW-XPASS",
        "value": 15003125537.6028
      },
      {
        "symbol": "KRW-XRP",
        "value": 10069418830.6043
      },
      {
        "symbol": "KRW-BTC",
        "value": 6291942789.4741
      }
    ]
  },
  "top10": {
    "top10_total_24h": 1763490008434.4539,
    "rest_total_24h": 981554462921.5334,
    "top10_share_pct": 64.24267536778125,
    "coins": [
      {
        "symbol": "KRW-XRP",
        "value": 464428656466.639,
        "share_pct": 16.918802639187195
      },
      {
        "symbol": "KRW-BTC",
        "value": 309306315709.64795,
        "share_pct": 11.267807095192811
      },
      {
        "symbol": "KRW-USDT",
        "value": 274518516092.17767,
        "share_pct": 10.000512521991018
      },
      {
        "symbol": "KRW-ETH",
        "value": 199793021092.10544,
        "share_pct": 7.278316368893376
      },
      {
        "symbol": "KRW-FLOW",
        "value": 128938329025.81284,
        "share_pct": 4.697130788636016
      },
      {
        "symbol": "KRW-USDC",
        "value": 105366822065.08856,
        "share_pct": 3.838437707096229
      },
      {
        "symbol": "KRW-DOGE",
        "value": 88792383914.4287,
        "share_pct": 3.234642820579418
      },
      {
        "symbol": "KRW-SOL",
        "value": 74875645863.72475,
        "share_pct": 2.727666041298702
      },
      {
        "symbol": "KRW-SIGN",
        "value": 73575135321.54568,
        "share_pct": 2.680289375610782
      },
      {
        "symbol": "KRW-SXP",
        "value": 43895182883.28329,
        "share_pct": 1.5990700092957
      }
    ]
  }
}