{
  "schema": "krw_rolling24h_v1",
  "timestamp_kst": "2026-07-16T02:45:45+0900",
  "timestamp_label": "07/16 02:45 KST",
  "totals": {
    "combined_24h": 1339258146685.4924,
    "upbit_24h": 872308984322.0557,
    "bithumb_24h": 376811128222.01514,
    "coinone_24h": 79031782065.9886,
    "korbit_24h": 11106252075.435564
  },
  "stablecoins": {
    "total_stable_vol_24h": 143881649721.36862,
    "stable_dominance_pct": 10.743384318957396,
    "by_asset": {
      "USDC": 8559222520.4653225,
      "USDT": 135322427200.90329,
      "DAI": 0.0
    }
  },
  "by_exchange_top": {
    "upbit_top5": [
      {
        "symbol": "KRW-ETH",
        "value": 98601399481.63972
      },
      {
        "symbol": "KRW-BTC",
        "value": 89884150287.23576
      },
      {
        "symbol": "KRW-XRP",
        "value": 77141672867.23894
      },
      {
        "symbol": "KRW-USDT",
        "value": 47523234671.18049
      },
      {
        "symbol": "KRW-XEC",
        "value": 41769831515.331856
      }
    ],
    "bithumb_top5": [
      {
        "symbol": "KRW-USDT",
        "value": 53964765945.016785
      },
      {
        "symbol": "KRW-ETH",
        "value": 33405012680.046864
      },
      {
        "symbol": "KRW-BTC",
        "value": 32858362262.88683
      },
      {
        "symbol": "KRW-XRP",
        "value": 30702947785.83603
      },
      {
        "symbol": "KRW-WLD",
        "value": 18410158529.97985
      }
    ],
    "coinone_top5": [
      {
        "symbol": "KRW-RLUSD",
        "value": 31808502223.7204
      },
      {
        "symbol": "KRW-USDT",
        "value": 26758947382.8448
      },
      {
        "symbol": "KRW-USDC",
        "value": 6292986010.2677
      },
      {
        "symbol": "KRW-BTC",
        "value": 3998740270.1403
      },
      {
        "symbol": "KRW-ETH",
        "value": 2893536801.0113
      }
    ],
    "korbit_top5": [
      {
        "symbol": "KRW-USDT",
        "value": 7075479201.861229
      },
      {
        "symbol": "KRW-XRP",
        "value": 1238584147.4997652
      },
      {
        "symbol": "KRW-ETH",
        "value": 1056180925.05772
      },
      {
        "symbol": "KRW-BTC",
        "value": 980470276.6599
      },
      {
        "symbol": "KRW-SOL",
        "value": 177994573.68717
      }
    ]
  },
  "top10": {
    "top10_total_24h": 730937572052.4506,
    "rest_total_24h": 608320574633.0419,
    "top10_share_pct": 54.57779546545494,
    "coins": [
      {
        "symbol": "KRW-ETH",
        "value": 135956129887.75562,
        "share_pct": 10.15159999020586,
        "change_rate_24h": 0.0194384449
      },
      {
        "symbol": "KRW-USDT",
        "value": 135322427200.90329,
        "share_pct": 10.10428254894775,
        "change_rate_24h": 0.0020422056
      },
      {
        "symbol": "KRW-BTC",
        "value": 127721723096.92279,
        "share_pct": 9.536751627236253,
        "change_rate_24h": 0.0019274281
      },
      {
        "symbol": "KRW-XRP",
        "value": 111422184695.04974,
        "share_pct": 8.319694374890057,
        "change_rate_24h": 0.0055113288
      },
      {
        "symbol": "KRW-XEC",
        "value": 46608850937.87627,
        "share_pct": 3.480199172446905,
        "change_rate_24h": 0.1637220259
      },
      {
        "symbol": "KRW-B3",
        "value": 43981834462.952286,
        "share_pct": 3.2840445713772355,
        "change_rate_24h": -0.0886850153
      },
      {
        "symbol": "KRW-VANA",
        "value": 36940951460.71242,
        "share_pct": 2.758314485682761,
        "change_rate_24h": 0.0317113177
      },
      {
        "symbol": "KRW-WLD",
        "value": 34997565047.82243,
        "share_pct": 2.6132053132876076,
        "change_rate_24h": -0.0245901639
      },
      {
        "symbol": "KRW-RLUSD",
        "value": 31808502223.7204,
        "share_pct": 2.3750837209721465,
        "change_rate_24h": null
      },
      {
        "symbol": "KRW-SLX",
        "value": 26177403038.735355,
        "share_pct": 1.9546196604083668,
        "change_rate_24h": -0.099009901
      }
    ]
  },
  "winner_loser": {
    "basis": "upbit_24h_change_rate",
    "filter": "stable_excluded, min_volume_5B",
    "winners": [
      {
        "symbol": "KRW-FLOCK",
        "change_rate_24h": 0.1691648822,
        "upbit_volume_24h": 16089993033.016941
      },
      {
        "symbol": "KRW-XEC",
        "change_rate_24h": 0.1637220259,
        "upbit_volume_24h": 41769831515.331856
      },
      {
        "symbol": "KRW-0G",
        "change_rate_24h": 0.1042471042,
        "upbit_volume_24h": 20911255249.266857
      },
      {
        "symbol": "KRW-MET2",
        "change_rate_24h": 0.0730593607,
        "upbit_volume_24h": 6093781745.192552
      },
      {
        "symbol": "KRW-ONDO",
        "change_rate_24h": 0.0562770563,
        "upbit_volume_24h": 14448998732.276525
      }
    ],
    "losers": [
      {
        "symbol": "KRW-ZBT",
        "change_rate_24h": -0.1625,
        "upbit_volume_24h": 18605843605.046185
      },
      {
        "symbol": "KRW-SLX",
        "change_rate_24h": -0.099009901,
        "upbit_volume_24h": 21418132494.672794
      },
      {
        "symbol": "KRW-B3",
        "change_rate_24h": -0.0886850153,
        "upbit_volume_24h": 35137715813.236275
      },
      {
        "symbol": "KRW-RE",
        "change_rate_24h": -0.0683870968,
        "upbit_volume_24h": 5160034416.753138
      },
      {
        "symbol": "KRW-DRV",
        "change_rate_24h": -0.0657894737,
        "upbit_volume_24h": 20253448717.357754
      }
    ]
  }
}