{
  "schema": "krw_rolling24h_v1",
  "timestamp_kst": "2026-06-10T02:23:57+0900",
  "timestamp_label": "06/10 02:23 KST",
  "totals": {
    "combined_24h": 2739095108086.2437,
    "upbit_24h": 1585746778769.0452,
    "bithumb_24h": 997965327324.5923,
    "coinone_24h": 132436822046.6144,
    "korbit_24h": 22946179945.99442
  },
  "stablecoins": {
    "total_stable_vol_24h": 236575087462.06046,
    "stable_dominance_pct": 8.636979663964688,
    "by_asset": {
      "USDC": 8786055599.311224,
      "USDT": 227789031862.74924,
      "DAI": 0.0
    }
  },
  "by_exchange_top": {
    "upbit_top5": [
      {
        "symbol": "KRW-SAHARA",
        "value": 225678592495.6325
      },
      {
        "symbol": "KRW-WLD",
        "value": 221741525092.11313
      },
      {
        "symbol": "KRW-XRP",
        "value": 135444829318.26768
      },
      {
        "symbol": "KRW-BTC",
        "value": 128076732172.22298
      },
      {
        "symbol": "KRW-MOVE",
        "value": 100989194487.39793
      }
    ],
    "bithumb_top5": [
      {
        "symbol": "KRW-H",
        "value": 190234952580.1006
      },
      {
        "symbol": "KRW-WLD",
        "value": 166589170669.17688
      },
      {
        "symbol": "KRW-USDT",
        "value": 99437937379.47682
      },
      {
        "symbol": "KRW-XRP",
        "value": 57230335447.819695
      },
      {
        "symbol": "KRW-BTC",
        "value": 55751772221.33735
      }
    ],
    "coinone_top5": [
      {
        "symbol": "KRW-RLUSD",
        "value": 51965149546.6487
      },
      {
        "symbol": "KRW-USDT",
        "value": 40452616300.9681
      },
      {
        "symbol": "KRW-BTC",
        "value": 7108649256.6172
      },
      {
        "symbol": "KRW-WLD",
        "value": 6148081055.7187
      },
      {
        "symbol": "KRW-USDC",
        "value": 5414260541.6617
      }
    ],
    "korbit_top5": [
      {
        "symbol": "KRW-USDT",
        "value": 12976928028.63094
      },
      {
        "symbol": "KRW-SPACE",
        "value": 2412594158.5877166
      },
      {
        "symbol": "KRW-BTC",
        "value": 1910942625.38496
      },
      {
        "symbol": "KRW-XRP",
        "value": 1626494902.8040113
      },
      {
        "symbol": "KRW-WLD",
        "value": 1329629574.943836
      }
    ]
  },
  "top10": {
    "top10_total_24h": 1831347265487.5457,
    "rest_total_24h": 907747842598.698,
    "top10_share_pct": 66.85957198350351,
    "coins": [
      {
        "symbol": "KRW-WLD",
        "value": 395808406391.9526,
        "share_pct": 14.450334536521325
      },
      {
        "symbol": "KRW-SAHARA",
        "value": 278066250315.1287,
        "share_pct": 10.151755939187106
      },
      {
        "symbol": "KRW-USDT",
        "value": 227789031862.74924,
        "share_pct": 8.316214767069601
      },
      {
        "symbol": "KRW-XRP",
        "value": 199104667609.3343,
        "share_pct": 7.2689943120830565
      },
      {
        "symbol": "KRW-H",
        "value": 193419570537.1268,
        "share_pct": 7.06144047229764
      },
      {
        "symbol": "KRW-BTC",
        "value": 192848096275.56247,
        "share_pct": 7.040576857161486
      },
      {
        "symbol": "KRW-MOVE",
        "value": 120172096503.48,
        "share_pct": 4.387291852287746
      },
      {
        "symbol": "KRW-ETH",
        "value": 99429697699.08368,
        "share_pct": 3.6300199071420134
      },
      {
        "symbol": "KRW-SLX",
        "value": 65698022392.12309,
        "share_pct": 2.3985301641469876
      },
      {
        "symbol": "KRW-XLM",
        "value": 59011425901.00489,
        "share_pct": 2.1544131756065643
      }
    ]
  }
}