{
  "schema": "krw_rolling24h_v1",
  "timestamp_kst": "2026-05-19T06:04:21+0900",
  "timestamp_label": "05/19 06:04 KST",
  "totals": {
    "combined_24h": 2315536076882.5703,
    "upbit_24h": 1431189952522.256,
    "bithumb_24h": 786598181505.2427,
    "coinone_24h": 97747942855.07008
  },
  "stablecoins": {
    "total_stable_vol_24h": 217453346037.96548,
    "stable_dominance_pct": 9.39105843389515,
    "by_asset": {
      "USDC": 9260978127.65398,
      "USDT": 208192367910.3115
    }
  },
  "by_exchange_top": {
    "upbit_top5": [
      {
        "symbol": "KRW-BTC",
        "value": 223011389551.08206
      },
      {
        "symbol": "KRW-XRP",
        "value": 176173643131.2925
      },
      {
        "symbol": "KRW-ETH",
        "value": 124482955787.74115
      },
      {
        "symbol": "KRW-TRAC",
        "value": 114379857962.27545
      },
      {
        "symbol": "KRW-USDT",
        "value": 82860704459.28319
      }
    ],
    "bithumb_top5": [
      {
        "symbol": "KRW-BTC",
        "value": 141305576005.38864
      },
      {
        "symbol": "KRW-USDT",
        "value": 94067365114.8188
      },
      {
        "symbol": "KRW-XRP",
        "value": 70760363536.78653
      },
      {
        "symbol": "KRW-ETH",
        "value": 59739925218.4525
      },
      {
        "symbol": "KRW-TRAC",
        "value": 32005174192.817375
      }
    ],
    "coinone_top5": [
      {
        "symbol": "KRW-USDT",
        "value": 31264298336.2095
      },
      {
        "symbol": "KRW-RLUSD",
        "value": 25169429842.2406
      },
      {
        "symbol": "KRW-BTC",
        "value": 9835594705.813
      },
      {
        "symbol": "KRW-USDC",
        "value": 6425802692.9054
      },
      {
        "symbol": "KRW-XRP",
        "value": 6347830828.4714
      }
    ]
  },
  "top10": {
    "top10_total_24h": 1438266147296.9258,
    "rest_total_24h": 877269929585.6445,
    "top10_share_pct": 62.113743839106064,
    "coins": [
      {
        "symbol": "KRW-BTC",
        "value": 374152560262.2837,
        "share_pct": 16.158355898561904
      },
      {
        "symbol": "KRW-XRP",
        "value": 253281837496.55045,
        "share_pct": 10.938367146390842
      },
      {
        "symbol": "KRW-USDT",
        "value": 208192367910.3115,
        "share_pct": 8.991108797173354
      },
      {
        "symbol": "KRW-ETH",
        "value": 188935303171.05667,
        "share_pct": 8.159462729055043
      },
      {
        "symbol": "KRW-TRAC",
        "value": 146385032155.09283,
        "share_pct": 6.321863589885091
      },
      {
        "symbol": "KRW-DOGE",
        "value": 87708088064.65671,
        "share_pct": 3.787809179062284
      },
      {
        "symbol": "KRW-IRYS",
        "value": 56902745189.63755,
        "share_pct": 2.4574328924404534
      },
      {
        "symbol": "KRW-SOL",
        "value": 54053455992.550476,
        "share_pct": 2.3343819399835564
      },
      {
        "symbol": "KRW-ONDO",
        "value": 37455467410.49727,
        "share_pct": 1.6175721805606218
      },
      {
        "symbol": "KRW-OPEN",
        "value": 31199289644.28852,
        "share_pct": 1.3473894859929127
      }
    ]
  }
}