{
  "schema": "krw_rolling24h_v1",
  "timestamp_kst": "2026-05-26T23:09:25+0900",
  "timestamp_label": "05/26 23:09 KST",
  "totals": {
    "combined_24h": 2153013868251.9739,
    "upbit_24h": 1301913600456.4863,
    "bithumb_24h": 745251772949.6891,
    "coinone_24h": 105848494845.79767
  },
  "stablecoins": {
    "total_stable_vol_24h": 168113927523.37262,
    "stable_dominance_pct": 7.808306764872995,
    "by_asset": {
      "USDC": 14894852851.925919,
      "USDT": 153219074671.4467
    }
  },
  "by_exchange_top": {
    "upbit_top5": [
      {
        "symbol": "KRW-BTC",
        "value": 108765359134.64069
      },
      {
        "symbol": "KRW-XRP",
        "value": 101233437821.86768
      },
      {
        "symbol": "KRW-NEAR",
        "value": 94663890553.50679
      },
      {
        "symbol": "KRW-WLD",
        "value": 86885556852.09418
      },
      {
        "symbol": "KRW-ONDO",
        "value": 73074105920.95363
      }
    ],
    "bithumb_top5": [
      {
        "symbol": "KRW-WLD",
        "value": 102243424078.13168
      },
      {
        "symbol": "KRW-USDT",
        "value": 69596392152.10919
      },
      {
        "symbol": "KRW-XRP",
        "value": 43500803097.82323
      },
      {
        "symbol": "KRW-BTC",
        "value": 38935029132.39848
      },
      {
        "symbol": "KRW-STAT",
        "value": 28820372199.727837
      }
    ],
    "coinone_top5": [
      {
        "symbol": "KRW-RLUSD",
        "value": 39832301568.0185
      },
      {
        "symbol": "KRW-USDT",
        "value": 27743722106.3316
      },
      {
        "symbol": "KRW-USDC",
        "value": 11382332480.7373
      },
      {
        "symbol": "KRW-BTC",
        "value": 6901905621.3172
      },
      {
        "symbol": "KRW-XRP",
        "value": 4270882626.8519
      }
    ]
  },
  "top10": {
    "top10_total_24h": 1083089428252.4781,
    "rest_total_24h": 1069924439999.4957,
    "top10_share_pct": 50.3057339399228,
    "coins": [
      {
        "symbol": "KRW-WLD",
        "value": 192598689161.34006,
        "share_pct": 8.945538716743632
      },
      {
        "symbol": "KRW-BTC",
        "value": 154602293888.35638,
        "share_pct": 7.180738413630265
      },
      {
        "symbol": "KRW-USDT",
        "value": 153219074671.4467,
        "share_pct": 7.116492695694748
      },
      {
        "symbol": "KRW-XRP",
        "value": 149005123546.54282,
        "share_pct": 6.920769333804603
      },
      {
        "symbol": "KRW-NEAR",
        "value": 107798508801.11969,
        "share_pct": 5.006865510283081
      },
      {
        "symbol": "KRW-ONDO",
        "value": 97193934406.15205,
        "share_pct": 4.51431994188981
      },
      {
        "symbol": "KRW-ETH",
        "value": 90708666047.99905,
        "share_pct": 4.213101800484228
      },
      {
        "symbol": "KRW-IN",
        "value": 49807460758.04526,
        "share_pct": 2.3133831831043334
      },
      {
        "symbol": "KRW-DRIFT",
        "value": 48323375403.457535,
        "share_pct": 2.244452584167103
      },
      {
        "symbol": "KRW-RLUSD",
        "value": 39832301568.0185,
        "share_pct": 1.850071760120999
      }
    ]
  }
}