{
  "schema": "krw_rolling24h_v1",
  "timestamp_kst": "2026-03-08T05:28:42+0900",
  "timestamp_label": "03/08 05:28 KST",
  "totals": {
    "combined_24h": 2065326025778.6812,
    "upbit_24h": 1329844820397.7756,
    "bithumb_24h": 468653369171.4582,
    "coinone_24h": 266827836209.44745
  },
  "stablecoins": {
    "total_stable_vol_24h": 361807572856.0439,
    "stable_dominance_pct": 17.51818203712574,
    "by_asset": {
      "USDC": 218388046236.1287,
      "USDT": 143419526619.9152
    }
  },
  "by_exchange_top": {
    "upbit_top5": [
      {
        "symbol": "KRW-BTC",
        "value": 111283601186.42313
      },
      {
        "symbol": "KRW-XRP",
        "value": 90941798833.24521
      },
      {
        "symbol": "KRW-SIGN",
        "value": 71773747111.63528
      },
      {
        "symbol": "KRW-ETH",
        "value": 65891259718.39866
      },
      {
        "symbol": "KRW-USDT",
        "value": 63813471678.11818
      }
    ],
    "bithumb_top5": [
      {
        "symbol": "KRW-USDT",
        "value": 66811905652.20853
      },
      {
        "symbol": "KRW-XRP",
        "value": 45134255151.811226
      },
      {
        "symbol": "KRW-BTC",
        "value": 39447227474.07164
      },
      {
        "symbol": "KRW-ETH",
        "value": 25123534797.982674
      },
      {
        "symbol": "KRW-SOLV",
        "value": 16321197901.85266
      }
    ],
    "coinone_top5": [
      {
        "symbol": "KRW-USDC",
        "value": 216975768850.6909
      },
      {
        "symbol": "KRW-EDGE",
        "value": 16069012868.8257
      },
      {
        "symbol": "KRW-USDT",
        "value": 12794149289.5885
      },
      {
        "symbol": "KRW-BTC",
        "value": 3957878916.3518
      },
      {
        "symbol": "KRW-RIVER",
        "value": 3837160758.4506
      }
    ]
  },
  "top10": {
    "top10_total_24h": 1084264047328.8036,
    "rest_total_24h": 981061978449.8776,
    "top10_share_pct": 52.49844498134419,
    "coins": [
      {
        "symbol": "KRW-USDC",
        "value": 218388046236.1287,
        "share_pct": 10.574022866621785
      },
      {
        "symbol": "KRW-BTC",
        "value": 154688707576.84656,
        "share_pct": 7.489796073165975
      },
      {
        "symbol": "KRW-USDT",
        "value": 143419526619.9152,
        "share_pct": 6.944159170503957
      },
      {
        "symbol": "KRW-XRP",
        "value": 139482939782.81992,
        "share_pct": 6.753555518201115
      },
      {
        "symbol": "KRW-ETH",
        "value": 94209498701.64043,
        "share_pct": 4.561483152090771
      },
      {
        "symbol": "KRW-SIGN",
        "value": 81829817033.9946,
        "share_pct": 3.962077464411104
      },
      {
        "symbol": "KRW-KAVA",
        "value": 66793996392.71042,
        "share_pct": 3.2340654966339937
      },
      {
        "symbol": "KRW-KITE",
        "value": 65582554243.79185,
        "share_pct": 3.1754092780129244
      },
      {
        "symbol": "KRW-SENT",
        "value": 60362519635.75971,
        "share_pct": 2.9226630024672007
      },
      {
        "symbol": "KRW-SKR",
        "value": 59506441105.19615,
        "share_pct": 2.8812129592353677
      }
    ]
  }
}