{
  "schema": "krw_rolling24h_v1",
  "timestamp_kst": "2026-02-13T05:38:07+0900",
  "timestamp_label": "02/13 05:38 KST",
  "totals": {
    "combined_24h": 4835141983870.086,
    "upbit_24h": 3153086716694.293,
    "bithumb_24h": 1610326150779.5366,
    "coinone_24h": 71729116396.25206
  },
  "stablecoins": {
    "total_stable_vol_24h": 518923835348.5261,
    "stable_dominance_pct": 10.732339134603352,
    "by_asset": {
      "USDC": 23283505026.78366,
      "USDT": 495640330321.7425
    }
  },
  "by_exchange_top": {
    "upbit_top5": [
      {
        "symbol": "KRW-BERA",
        "value": 553384888379.2473
      },
      {
        "symbol": "KRW-XRP",
        "value": 258555470048.04556
      },
      {
        "symbol": "KRW-BTC",
        "value": 225016229816.4491
      },
      {
        "symbol": "KRW-0G",
        "value": 188912294245.41724
      },
      {
        "symbol": "KRW-ME",
        "value": 172553774618.40222
      }
    ],
    "bithumb_top5": [
      {
        "symbol": "KRW-USDT",
        "value": 335777461285.4316
      },
      {
        "symbol": "KRW-BTC",
        "value": 234846841686.1216
      },
      {
        "symbol": "KRW-XRP",
        "value": 231529870990.8222
      },
      {
        "symbol": "KRW-ETH",
        "value": 127271076580.85094
      },
      {
        "symbol": "KRW-BERA",
        "value": 119431553536.36821
      }
    ],
    "coinone_top5": [
      {
        "symbol": "KRW-USDT",
        "value": 18819051185.1935
      },
      {
        "symbol": "KRW-USDC",
        "value": 18452554182.7239
      },
      {
        "symbol": "KRW-BTC",
        "value": 8542842959.1306
      },
      {
        "symbol": "KRW-XRP",
        "value": 7044323396.2179
      },
      {
        "symbol": "KRW-ETH",
        "value": 4294781911.3898
      }
    ]
  },
  "top10": {
    "top10_total_24h": 3125683638090.2373,
    "rest_total_24h": 1709458345779.8486,
    "top10_share_pct": 64.64512621382042,
    "coins": [
      {
        "symbol": "KRW-BERA",
        "value": 673602314937.5498,
        "share_pct": 13.931386445003485
      },
      {
        "symbol": "KRW-XRP",
        "value": 497129664435.0857,
        "share_pct": 10.28159392409774
      },
      {
        "symbol": "KRW-USDT",
        "value": 495640330321.7425,
        "share_pct": 10.25079164118006
      },
      {
        "symbol": "KRW-BTC",
        "value": 468405914461.7013,
        "share_pct": 9.687531742072764
      },
      {
        "symbol": "KRW-ETH",
        "value": 287593433953.9897,
        "share_pct": 5.947983221865961
      },
      {
        "symbol": "KRW-0G",
        "value": 214041765649.4292,
        "share_pct": 4.426793801784255
      },
      {
        "symbol": "KRW-ME",
        "value": 202723190680.6695,
        "share_pct": 4.192703985879816
      },
      {
        "symbol": "KRW-SOL",
        "value": 104655740015.57745,
        "share_pct": 2.164481216160899
      },
      {
        "symbol": "KRW-LINEA",
        "value": 91755939305.8569,
        "share_pct": 1.8976886224221015
      },
      {
        "symbol": "KRW-MOVE",
        "value": 90135344328.63522,
        "share_pct": 1.8641716133533308
      }
    ]
  }
}