{
  "schema": "krw_rolling24h_v1",
  "timestamp_kst": "2026-06-15T02:56:32+0900",
  "timestamp_label": "06/15 02:56 KST",
  "totals": {
    "combined_24h": 1751816776114.241,
    "upbit_24h": 1006270630784.23,
    "bithumb_24h": 623248049342.4,
    "coinone_24h": 112552929796.10208,
    "korbit_24h": 9745166191.507357
  },
  "stablecoins": {
    "total_stable_vol_24h": 129284454376.83403,
    "stable_dominance_pct": 7.380021480534276,
    "by_asset": {
      "USDC": 22240616342.043274,
      "USDT": 107043838034.79076,
      "DAI": 0.0
    }
  },
  "by_exchange_top": {
    "upbit_top5": [
      {
        "symbol": "KRW-WLD",
        "value": 78731115115.44595
      },
      {
        "symbol": "KRW-BTC",
        "value": 75939121212.67882
      },
      {
        "symbol": "KRW-MEGA",
        "value": 75139522514.38753
      },
      {
        "symbol": "KRW-XRP",
        "value": 57709855032.41079
      },
      {
        "symbol": "KRW-TRUMP",
        "value": 46598862198.96242
      }
    ],
    "bithumb_top5": [
      {
        "symbol": "KRW-H",
        "value": 149732097553.15686
      },
      {
        "symbol": "KRW-WLD",
        "value": 63639313568.58752
      },
      {
        "symbol": "KRW-USDT",
        "value": 51140456632.74706
      },
      {
        "symbol": "KRW-MEGA",
        "value": 30649804846.412125
      },
      {
        "symbol": "KRW-BTC",
        "value": 26556661772.28261
      }
    ],
    "coinone_top5": [
      {
        "symbol": "KRW-RLUSD",
        "value": 52136689652.016
      },
      {
        "symbol": "KRW-USDC",
        "value": 21057741708.6006
      },
      {
        "symbol": "KRW-USDT",
        "value": 12134758891.3869
      },
      {
        "symbol": "KRW-MEME",
        "value": 10554542301.7927
      },
      {
        "symbol": "KRW-BTC",
        "value": 4480535065.457
      }
    ],
    "korbit_top5": [
      {
        "symbol": "KRW-SPACE",
        "value": 3084797626.2477126
      },
      {
        "symbol": "KRW-USDT",
        "value": 2928914474.2492504
      },
      {
        "symbol": "KRW-XRP",
        "value": 1025244607.835673
      },
      {
        "symbol": "KRW-BTC",
        "value": 913980997.86461
      },
      {
        "symbol": "KRW-SOL",
        "value": 429583195.086867
      }
    ]
  },
  "top10": {
    "top10_total_24h": 916172203953.6292,
    "rest_total_24h": 835644572160.6118,
    "top10_share_pct": 52.298403374456726,
    "coins": [
      {
        "symbol": "KRW-H",
        "value": 150709235610.48706,
        "share_pct": 8.603025023243577
      },
      {
        "symbol": "KRW-WLD",
        "value": 144411050636.26065,
        "share_pct": 8.243501980645675
      },
      {
        "symbol": "KRW-BTC",
        "value": 107890299048.28304,
        "share_pct": 6.158766174599483
      },
      {
        "symbol": "KRW-USDT",
        "value": 107043838034.79076,
        "share_pct": 6.110447136613682
      },
      {
        "symbol": "KRW-MEGA",
        "value": 105789327360.79965,
        "share_pct": 6.038835156919449
      },
      {
        "symbol": "KRW-XRP",
        "value": 86511318859.26425,
        "share_pct": 4.938377120189343
      },
      {
        "symbol": "KRW-TRUMP",
        "value": 55092149872.06263,
        "share_pct": 3.144857991043118
      },
      {
        "symbol": "KRW-ETH",
        "value": 53482348463.28153,
        "share_pct": 3.0529647388074674
      },
      {
        "symbol": "KRW-ZKC",
        "value": 53105946416.383644,
        "share_pct": 3.0314783566680754
      },
      {
        "symbol": "KRW-RLUSD",
        "value": 52136689652.016,
        "share_pct": 2.9761496957268556
      }
    ]
  }
}