{
  "updatedAt": "2026-03-06T05:38:45Z",
  "type": "us-btc-spot",
  "totalNetAssets": {
    "value": "91439688680.3418806200000000",
    "lastUpdateDate": "2026-03-05",
    "status": "1"
  },
  "totalNetAssetsPercentage": {
    "value": "0.06418530",
    "lastUpdateDate": "2026-03-05",
    "status": "1"
  },
  "dailyNetInflow": {
    "value": "-227833838.7399999970000000",
    "lastUpdateDate": "2026-03-05",
    "status": "1"
  },
  "cumNetInflow": {
    "value": "917277292.5099999880000000",
    "lastUpdateDate": "2026-03-05",
    "status": "1"
  },
  "dailyTotalValueTraded": {
    "value": "6496478788.0000000000000000",
    "lastUpdateDate": "2026-03-05",
    "status": "1"
  },
  "totalTokenHoldings": {
    "value": "1283607.09045270",
    "lastUpdateDate": "2026-03-05",
    "status": "1"
  },
  "list": [
    {
      "id": 1746110179689463810,
      "ticker": "IBIT",
      "institute": "BlackRock ",
      "fee": {
        "value": "0.00250000",
        "lastUpdateDate": "2026-03-05",
        "status": "1"
      },
      "netAssetsPercentage": {
        "value": "0.03874499",
        "lastUpdateDate": "2026-03-05",
        "status": "1"
      },
      "netAssets": {
        "value": "55196905680.0000000000000000",
        "lastUpdateDate": "2026-03-05",
        "status": "1"
      },
      "dailyNetInflow": {
        "value": "-88743600.0000000000000000",
        "lastUpdateDate": "2026-03-05",
        "status": "1"
      },
      "cumNetInflow": {
        "value": "803409360.0000000000000000",
        "lastUpdateDate": "2026-03-05",
        "status": "1"
      },
      "dailyValueTraded": {
        "value": "4766213237.0000000000000000",
        "lastUpdateDate": "2026-03-05",
        "status": "1"
      },
      "discountPremiumRate": {
        "value": "0.0012891070454656983",
        "lastUpdateDate": "2026-03-05",
        "status": "1"
      }
    },
    {
      "id": 1746110179697852417,
      "ticker": "FBTC",
      "institute": "Fidelity",
      "fee": {
        "value": "0.00000000",
        "lastUpdateDate": "2026-03-05",
        "status": "1"
      },
      "netAssetsPercentage": {
        "value": "0.00938011",
        "lastUpdateDate": "2026-03-05",
        "status": "1"
      },
      "netAssets": {
        "value": "13363101959.1148800000000000",
        "lastUpdateDate": "2026-03-05",
        "status": "1"
      },
      "dailyNetInflow": {
        "value": "-48028924.6500000000000000",
        "lastUpdateDate": "2026-03-05",
        "status": "1"
      },
      "cumNetInflow": {
        "value": "5481727.4249999900000000",
        "lastUpdateDate": "2026-03-05",
        "status": "1"
      },
      "dailyValueTraded": {
        "value": "444663235.0000000000000000",
        "lastUpdateDate": "2026-03-05",
        "status": "1"
      },
      "discountPremiumRate": {
        "value": "0.0012455947210137097",
        "lastUpdateDate": "2026-03-05",
        "status": "1"
      }
    },
    {
      "id": 1746110179697852418,
      "ticker": "ARKB",
      "institute": "Ark & 21Shares",
      "fee": {
        "value": "0.00210000",
        "lastUpdateDate": "2026-03-05",
        "status": "1"
      },
      "netAssetsPercentage": {
        "value": "0.00178106",
        "lastUpdateDate": "2026-03-05",
        "status": "1"
      },
      "netAssets": {
        "value": "2537328180.9600000000000000",
        "lastUpdateDate": "2026-03-05",
        "status": "1"
      },
      "dailyNetInflow": {
        "value": "-22671584.6399999970000000",
        "lastUpdateDate": "2026-03-05",
        "status": "1"
      },
      "cumNetInflow": {
        "value": "-2306846.7899999970000000",
        "lastUpdateDate": "2026-03-05",
        "status": "1"
      },
      "dailyValueTraded": {
        "value": "276724997.0000000000000000",
        "lastUpdateDate": "2026-03-05",
        "status": "1"
      },
      "discountPremiumRate": {
        "value": "0.001006299310889247",
        "lastUpdateDate": "2026-03-05",
        "status": "1"
      }
    },
    {
      "id": 1746110179702046721,
      "ticker": "BTCO",
      "institute": "Invesco",
      "fee": {
        "value": "0.00250000",
        "lastUpdateDate": "2026-03-05",
        "status": "1"
      },
      "netAssetsPercentage": {
        "value": "0.00033563",
        "lastUpdateDate": "2026-03-05",
        "status": "1"
      },
      "netAssets": {
        "value": "478151627.7200000000000000",
        "lastUpdateDate": "2026-03-05",
        "status": "1"
      },
      "dailyNetInflow": {
        "value": "0.0000000000000000",
        "lastUpdateDate": "2026-03-05",
        "status": "1"
      },
      "cumNetInflow": {
        "value": "15291395.9350000000000000",
        "lastUpdateDate": "2026-03-05",
        "status": "1"
      },
      "dailyValueTraded": {
        "value": "9309258.0000000000000000",
        "lastUpdateDate": "2026-03-05",
        "status": "1"
      },
      "discountPremiumRate": {
        "value": "0.0002483846820018343",
        "lastUpdateDate": "2026-03-05",
        "status": "1"
      }
    },
    {
      "id": 1746110179706241026,
      "ticker": "BTCW",
      "institute": "WisdomTree",
      "fee": {
        "value": "0.00250000",
        "lastUpdateDate": "2026-03-05",
        "status": "1"
      },
      "netAssetsPercentage": {
        "value": "0.00010804",
        "lastUpdateDate": "2026-03-05",
        "status": "1"
      },
      "netAssets": {
        "value": "153914747.0750000200000000",
        "lastUpdateDate": "2026-03-05",
        "status": "1"
      },
      "dailyNetInflow": {
        "value": "0.0000000000000000",
        "lastUpdateDate": "2026-03-05",
        "status": "1"
      },
      "cumNetInflow": {
        "value": "16447935.6000000000000000",
        "lastUpdateDate": "2026-03-05",
        "status": "1"
      },
      "dailyValueTraded": {
        "value": "13434809.0000000000000000",
        "lastUpdateDate": "2026-03-05",
        "status": "1"
      },
      "discountPremiumRate": {
        "value": "0.0018078645502657142",
        "lastUpdateDate": "2026-03-05",
        "status": "1"
      }
    },
    {
      "id": 1746110179706241027,
      "ticker": "BRRR",
      "institute": "Valkyrie",
      "fee": {
        "value": "0.00250000",
        "lastUpdateDate": "2026-03-05",
        "status": "1"
      },
      "netAssetsPercentage": {
        "value": "0.00031408",
        "lastUpdateDate": "2026-03-05",
        "status": "1"
      },
      "netAssets": {
        "value": "447444915.5000000000000000",
        "lastUpdateDate": "2026-03-05",
        "status": "1"
      },
      "dailyNetInflow": {
        "value": "5421141.0000000000000000",
        "lastUpdateDate": "2026-03-05",
        "status": "1"
      },
      "cumNetInflow": {
        "value": "16993520.9999999980000000",
        "lastUpdateDate": "2026-03-05",
        "status": "1"
      },
      "dailyValueTraded": {
        "value": "8987347.0000000000000000",
        "lastUpdateDate": "2026-03-05",
        "status": "1"
      },
      "discountPremiumRate": {
        "value": "0.0015788687289264303",
        "lastUpdateDate": "2026-03-05",
        "status": "1"
      }
    },
    {
      "id": 1746110179710435329,
      "ticker": "BITB",
      "institute": "Bitwise",
      "fee": {
        "value": "0.00200000",
        "lastUpdateDate": "2026-03-05",
        "status": "1"
      },
      "netAssetsPercentage": {
        "value": "0.00195179",
        "lastUpdateDate": "2026-03-05",
        "status": "1"
      },
      "netAssets": {
        "value": "2780559846.2400002000000000",
        "lastUpdateDate": "2026-03-05",
        "status": "1"
      },
      "dailyNetInflow": {
        "value": "-46381315.2000000000000000",
        "lastUpdateDate": "2026-03-05",
        "status": "1"
      },
      "cumNetInflow": {
        "value": "-1997052.9099999990000000",
        "lastUpdateDate": "2026-03-05",
        "status": "1"
      },
      "dailyValueTraded": {
        "value": "257903242.0000000000000000",
        "lastUpdateDate": "2026-03-05",
        "status": "1"
      },
      "discountPremiumRate": {
        "value": "0.0012652940035644544",
        "lastUpdateDate": "2026-03-05",
        "status": "1"
      }
    },
    {
      "id": 1746110179710435330,
      "ticker": "EZBC",
      "institute": "Franklin",
      "fee": {
        "value": "0.00190000",
        "lastUpdateDate": "2026-03-05",
        "status": "1"
      },
      "netAssetsPercentage": {
        "value": "0.00031047",
        "lastUpdateDate": "2026-03-05",
        "status": "1"
      },
      "netAssets": {
        "value": "442297742.0000000000000000",
        "lastUpdateDate": "2026-03-05",
        "status": "1"
      },
      "dailyNetInflow": {
        "value": "0.0000000000000000",
        "lastUpdateDate": "2026-03-05",
        "status": "1"
      },
      "cumNetInflow": {
        "value": "22476271.5000000000000000",
        "lastUpdateDate": "2026-03-05",
        "status": "1"
      },
      "dailyValueTraded": {
        "value": "17786109.0000000000000000",
        "lastUpdateDate": "2026-03-05",
        "status": "1"
      },
      "discountPremiumRate": {
        "value": "0.0016046820560073893",
        "lastUpdateDate": "2026-03-05",
        "status": "1"
      }
    },
    {
      "id": 1746110179714629633,
      "ticker": "HODL",
      "institute": "VanEck",
      "fee": {
        "value": "0.00250000",
        "lastUpdateDate": "2026-03-05",
        "status": "1"
      },
      "netAssetsPercentage": {
        "value": "0.00085065",
        "lastUpdateDate": "2026-03-05",
        "status": "1"
      },
      "netAssets": {
        "value": "1211855279.2500000000000000",
        "lastUpdateDate": "2026-03-05",
        "status": "1"
      },
      "dailyNetInflow": {
        "value": "-8551905.2500000000000000",
        "lastUpdateDate": "2026-03-05",
        "status": "1"
      },
      "cumNetInflow": {
        "value": "16180229.7500000000000000",
        "lastUpdateDate": "2026-03-05",
        "status": "1"
      },
      "dailyValueTraded": {
        "value": "83289017.0000000000000000",
        "lastUpdateDate": "2026-03-05",
        "status": "1"
      },
      "discountPremiumRate": {
        "value": "0.0013850422395640383",
        "lastUpdateDate": "2026-03-05",
        "status": "1"
      }
    },
    {
      "id": 1746110179718823937,
      "ticker": "GBTC",
      "institute": "Grayscale",
      "fee": {
        "value": "0.01500000",
        "lastUpdateDate": "2026-03-05",
        "status": "1"
      },
      "netAssetsPercentage": {
        "value": "0.00782394",
        "lastUpdateDate": "2026-03-05",
        "status": "1"
      },
      "netAssets": {
        "value": "11146147427.2500000000000000",
        "lastUpdateDate": "2026-03-05",
        "status": "1"
      },
      "dailyNetInflow": {
        "value": "-18877650.0000000000000000",
        "lastUpdateDate": "2026-03-05",
        "status": "1"
      },
      "cumNetInflow": {
        "value": "-25407109.0000000000000000",
        "lastUpdateDate": "2026-03-05",
        "status": "1"
      },
      "dailyValueTraded": {
        "value": "291292411.0000000000000000",
        "lastUpdateDate": "2026-03-05",
        "status": "1"
      },
      "discountPremiumRate": {
        "value": "0.00013508037282172758",
        "lastUpdateDate": "2026-03-05",
        "status": "1"
      }
    },
    {
      "id": 1746110179718823938,
      "ticker": "DEFI",
      "institute": "Hashdex",
      "fee": {
        "value": "0.00900000",
        "lastUpdateDate": "2026-03-05",
        "status": "1"
      },
      "netAssetsPercentage": {
        "value": "0.00000680",
        "lastUpdateDate": "2026-03-05",
        "status": "1"
      },
      "netAssets": {
        "value": "9680544.0000000000000000",
        "lastUpdateDate": "2026-03-05",
        "status": "1"
      },
      "dailyNetInflow": {
        "value": "0.0000000000000000",
        "lastUpdateDate": "2026-03-05",
        "status": "1"
      },
      "cumNetInflow": {
        "value": "0.0000000000000000",
        "lastUpdateDate": "2026-03-05",
        "status": "1"
      },
      "dailyValueTraded": {
        "value": "15899.0000000000000000",
        "lastUpdateDate": "2026-03-05",
        "status": "1"
      },
      "discountPremiumRate": {
        "value": "0.0027890994555677118",
        "lastUpdateDate": "2026-03-05",
        "status": "1"
      }
    },
    {
      "id": 1746110179718823939,
      "ticker": "BTC",
      "institute": "Grayscale",
      "fee": {
        "value": "0.00150000",
        "lastUpdateDate": "2026-03-05",
        "status": "1"
      },
      "netAssetsPercentage": {
        "value": "0.00257774",
        "lastUpdateDate": "2026-03-05",
        "status": "1"
      },
      "netAssets": {
        "value": "3672300731.2320004000000000",
        "lastUpdateDate": "2026-03-05",
        "status": "1"
      },
      "dailyNetInflow": {
        "value": "0.0000000000000000",
        "lastUpdateDate": "2026-03-05",
        "status": "1"
      },
      "cumNetInflow": {
        "value": "50707859.9999999960000000",
        "lastUpdateDate": "2026-03-05",
        "status": "1"
      },
      "dailyValueTraded": {
        "value": "326859227.0000000000000000",
        "lastUpdateDate": "2026-03-05",
        "status": "1"
      },
      "discountPremiumRate": {
        "value": "0.000025381354856746086",
        "lastUpdateDate": "2026-03-05",
        "status": "1"
      }
    }
  ]
}