{
  "updatedAt": "2026-07-09T07:26:09Z",
  "type": "us-avax-spot",
  "totalNetAssets": {
    "value": "31592453.242",
    "lastUpdateDate": "2026-07-08"
  },
  "dailyNetInflow": {
    "value": "0",
    "lastUpdateDate": "2026-07-08"
  },
  "cumNetInflow": {
    "value": "24858004.209999997"
  },
  "dailyTotalValueTraded": {
    "value": "44080.95"
  },
  "totalTokenHoldings": {
    "value": null
  },
  "totalNetAssetsPercentage": {
    "value": null
  },
  "list": [
    {
      "ticker": "BAVA",
      "institute": "Bitwise",
      "netAssets": {
        "value": "16378544.0200000000000000"
      },
      "dailyNetInflow": {
        "value": "0.0000000000000000",
        "lastUpdateDate": "2026-07-08"
      },
      "cumNetInflow": {
        "value": "10375281.7099999989700000"
      },
      "dailyValueTraded": {
        "value": "574.0000000000000000"
      },
      "fee": {
        "value": 0.0034
      }
    },
    {
      "ticker": "VAVX",
      "institute": "VanEck",
      "netAssets": {
        "value": "11020317.0000000000000000"
      },
      "dailyNetInflow": {
        "value": "0.0000000000000000",
        "lastUpdateDate": "2026-07-08"
      },
      "cumNetInflow": {
        "value": "0.0000000000000000"
      },
      "dailyValueTraded": {
        "value": "29689.0000000000000000"
      },
      "fee": {
        "value": 0.003
      }
    },
    {
      "ticker": "GAVA",
      "institute": "Grayscale",
      "netAssets": {
        "value": "4193592.2219999996000000"
      },
      "dailyNetInflow": {
        "value": "0.0000000000000000",
        "lastUpdateDate": "2026-07-08"
      },
      "cumNetInflow": {
        "value": "624022.9999999999700000"
      },
      "dailyValueTraded": {
        "value": "13818.0000000000000000"
      },
      "fee": {
        "value": 0
      }
    }
  ]
}