{
  "updatedAt": "2026-07-03T06:52:13Z",
  "type": "us-eth-spot",
  "totalNetAssets": {
    "value": "9019904969.8730010000000000",
    "lastUpdateDate": "2026-07-02",
    "status": "1"
  },
  "totalNetAssetsPercentage": {
    "value": "0.04381669",
    "lastUpdateDate": "2026-07-02",
    "status": "1"
  },
  "dailyNetInflow": {
    "value": "29082177.1600000001000000",
    "lastUpdateDate": "2026-07-02",
    "status": "1"
  },
  "cumNetInflow": {
    "value": "10889038108.336",
    "lastUpdateDate": "2026-07-02",
    "status": "1"
  },
  "dailyTotalValueTraded": {
    "value": "669661824.0000000000000000",
    "lastUpdateDate": "2026-07-02",
    "status": "1"
  },
  "totalTokenHoldings": {
    "value": "5287941.16687616",
    "lastUpdateDate": "2026-07-02",
    "status": "1"
  },
  "list": [
    {
      "id": 1746110440948465695,
      "ticker": "ETHE",
      "institute": "Grayscale",
      "fee": {
        "value": "0.02500000",
        "lastUpdateDate": "2026-07-02",
        "status": "1"
      },
      "netAssetsPercentage": {
        "value": "0.00638104",
        "lastUpdateDate": "2026-07-02",
        "status": "1"
      },
      "netAssets": {
        "value": "1313572201.7000000000000000",
        "lastUpdateDate": "2026-07-02",
        "status": "1"
      },
      "dailyNetInflow": {
        "value": "-2747240.0000000000000000",
        "lastUpdateDate": "2026-07-02",
        "status": "1"
      },
      "cumNetInflow": {
        "value": "-5332380067.0000000655000000",
        "lastUpdateDate": "2026-07-02",
        "status": "1"
      },
      "dailyValueTraded": {
        "value": "42286802.0000000000000000",
        "lastUpdateDate": "2026-07-02",
        "status": "1"
      },
      "discountPremiumRate": {
        "value": "0.0010046446615512572",
        "lastUpdateDate": "2026-07-02",
        "status": "1"
      }
    },
    {
      "id": 1746110440948465696,
      "ticker": "ETHW",
      "institute": "Bitwise",
      "fee": {
        "value": "0.00200000",
        "lastUpdateDate": "2026-07-02",
        "status": "1"
      },
      "netAssetsPercentage": {
        "value": "0.00088073",
        "lastUpdateDate": "2026-07-02",
        "status": "1"
      },
      "netAssets": {
        "value": "181302110.7200000000000000",
        "lastUpdateDate": "2026-07-02",
        "status": "1"
      },
      "dailyNetInflow": {
        "value": "0.0000000000000000",
        "lastUpdateDate": "2026-07-02",
        "status": "1"
      },
      "cumNetInflow": {
        "value": "384868125.1899999960500000",
        "lastUpdateDate": "2026-07-02",
        "status": "1"
      },
      "dailyValueTraded": {
        "value": "8822589.0000000000000000",
        "lastUpdateDate": "2026-07-02",
        "status": "1"
      },
      "discountPremiumRate": {
        "value": "0.0015128851997956438",
        "lastUpdateDate": "2026-07-02",
        "status": "1"
      }
    },
    {
      "id": 1746110440948465697,
      "ticker": "ETHA",
      "institute": "BlackRock",
      "fee": {
        "value": "0.00250000",
        "lastUpdateDate": "2026-07-02",
        "status": "1"
      },
      "netAssetsPercentage": {
        "value": "0.02257087",
        "lastUpdateDate": "2026-07-02",
        "status": "1"
      },
      "netAssets": {
        "value": "4646336911.3200010000000000",
        "lastUpdateDate": "2026-07-02",
        "status": "1"
      },
      "dailyNetInflow": {
        "value": "29741478.9600000000000000",
        "lastUpdateDate": "2026-07-02",
        "status": "1"
      },
      "cumNetInflow": {
        "value": "11124450952.7399999437000000",
        "lastUpdateDate": "2026-07-02",
        "status": "1"
      },
      "dailyValueTraded": {
        "value": "520975963.0000000000000000",
        "lastUpdateDate": "2026-07-02",
        "status": "1"
      },
      "discountPremiumRate": {
        "value": "0.003151189627323081",
        "lastUpdateDate": "2026-07-02",
        "status": "1"
      }
    },
    {
      "id": 1746110440948465698,
      "ticker": "ETHV",
      "institute": "VanEck",
      "fee": {
        "value": "0.00200000",
        "lastUpdateDate": "2026-07-02",
        "status": "1"
      },
      "netAssetsPercentage": {
        "value": "0.00041010",
        "lastUpdateDate": "2026-07-02",
        "status": "1"
      },
      "netAssets": {
        "value": "84420334.0000000000000000",
        "lastUpdateDate": "2026-07-02",
        "status": "1"
      },
      "dailyNetInflow": {
        "value": "1241475.5000000000000000",
        "lastUpdateDate": "2026-07-02",
        "status": "1"
      },
      "cumNetInflow": {
        "value": "164707075.7499999979000000",
        "lastUpdateDate": "2026-07-02",
        "status": "1"
      },
      "dailyValueTraded": {
        "value": "1798909.0000000000000000",
        "lastUpdateDate": "2026-07-02",
        "status": "1"
      },
      "discountPremiumRate": {
        "value": "-0.0003830119885571692",
        "lastUpdateDate": "2026-07-02",
        "status": "1"
      }
    },
    {
      "id": 1746110440948465699,
      "ticker": "TETH",
      "institute": "21Shares",
      "fee": {
        "value": "0.00210000",
        "lastUpdateDate": "2026-07-02",
        "status": "1"
      },
      "netAssetsPercentage": {
        "value": "0.00006755",
        "lastUpdateDate": "2026-07-02",
        "status": "1"
      },
      "netAssets": {
        "value": "13906037.2400000000000000",
        "lastUpdateDate": "2026-07-02",
        "status": "1"
      },
      "dailyNetInflow": {
        "value": "0.0000000000000000",
        "lastUpdateDate": "2026-07-02",
        "status": "1"
      },
      "cumNetInflow": {
        "value": "17002395.9799999986300000",
        "lastUpdateDate": "2026-07-02",
        "status": "1"
      },
      "dailyValueTraded": {
        "value": "6610778.0000000000000000",
        "lastUpdateDate": "2026-07-02",
        "status": "1"
      },
      "discountPremiumRate": {
        "value": "0.0006732874246206944",
        "lastUpdateDate": "2026-07-02",
        "status": "1"
      }
    },
    {
      "id": 1746110440948465700,
      "ticker": "QETH",
      "institute": "Invesco",
      "fee": {
        "value": "0.00250000",
        "lastUpdateDate": "2026-07-02",
        "status": "1"
      },
      "netAssetsPercentage": {
        "value": "0.00008071",
        "lastUpdateDate": "2026-07-02",
        "status": "1"
      },
      "netAssets": {
        "value": "16614869.4810000000000000",
        "lastUpdateDate": "2026-07-02",
        "status": "1"
      },
      "dailyNetInflow": {
        "value": "0.0000000000000000",
        "lastUpdateDate": "2026-07-02",
        "status": "1"
      },
      "cumNetInflow": {
        "value": "24617966.0300000008000000",
        "lastUpdateDate": "2026-07-02",
        "status": "1"
      },
      "dailyValueTraded": {
        "value": "751681.0000000000000000",
        "lastUpdateDate": "2026-07-02",
        "status": "1"
      },
      "discountPremiumRate": {
        "value": "-0.00013057466400701045",
        "lastUpdateDate": "2026-07-02",
        "status": "1"
      }
    },
    {
      "id": 1746110440948465701,
      "ticker": "FETH",
      "institute": "Fidelity",
      "fee": {
        "value": "0.00250000",
        "lastUpdateDate": "2026-07-02",
        "status": "1"
      },
      "netAssetsPercentage": {
        "value": "0.00392689",
        "lastUpdateDate": "2026-07-02",
        "status": "1"
      },
      "netAssets": {
        "value": "808371878.5000000000000000",
        "lastUpdateDate": "2026-07-02",
        "status": "1"
      },
      "dailyNetInflow": {
        "value": "846462.7000000001000000",
        "lastUpdateDate": "2026-07-02",
        "status": "1"
      },
      "cumNetInflow": {
        "value": "2111715254.7999998747400000",
        "lastUpdateDate": "2026-07-02",
        "status": "1"
      },
      "dailyValueTraded": {
        "value": "41089845.0000000000000000",
        "lastUpdateDate": "2026-07-02",
        "status": "1"
      },
      "discountPremiumRate": {
        "value": "0.0006348182855546725",
        "lastUpdateDate": "2026-07-02",
        "status": "1"
      }
    },
    {
      "id": 1746110440948465702,
      "ticker": "EZET",
      "institute": "Franklin",
      "fee": {
        "value": "0.00190000",
        "lastUpdateDate": "2026-07-02",
        "status": "1"
      },
      "netAssetsPercentage": {
        "value": "0.00016886",
        "lastUpdateDate": "2026-07-02",
        "status": "1"
      },
      "netAssets": {
        "value": "34760064.6000000000000000",
        "lastUpdateDate": "2026-07-02",
        "status": "1"
      },
      "dailyNetInflow": {
        "value": "0.0000000000000000",
        "lastUpdateDate": "2026-07-02",
        "status": "1"
      },
      "cumNetInflow": {
        "value": "65914409.7500000011000000",
        "lastUpdateDate": "2026-07-02",
        "status": "1"
      },
      "dailyValueTraded": {
        "value": "282006.0000000000000000",
        "lastUpdateDate": "2026-07-02",
        "status": "1"
      },
      "discountPremiumRate": {
        "value": "0.001235193331602824",
        "lastUpdateDate": "2026-07-02",
        "status": "1"
      }
    },
    {
      "id": 1746110440948465703,
      "ticker": "ETH",
      "institute": "Grayscale",
      "fee": {
        "value": "0.00150000",
        "lastUpdateDate": "2026-07-02",
        "status": "1"
      },
      "netAssetsPercentage": {
        "value": "0.00695831",
        "lastUpdateDate": "2026-07-02",
        "status": "1"
      },
      "netAssets": {
        "value": "1432406765.3520000000000000",
        "lastUpdateDate": "2026-07-02",
        "status": "1"
      },
      "dailyNetInflow": {
        "value": "0.0000000000000000",
        "lastUpdateDate": "2026-07-02",
        "status": "1"
      },
      "cumNetInflow": {
        "value": "1809367753.7759999891000000",
        "lastUpdateDate": "2026-07-02",
        "status": "1"
      },
      "dailyValueTraded": {
        "value": "34448400.0000000000000000",
        "lastUpdateDate": "2026-07-02",
        "status": "1"
      },
      "discountPremiumRate": {
        "value": "0.000692692098362091",
        "lastUpdateDate": "2026-07-02",
        "status": "1"
      }
    },
    {
      "id": 2032379649767452674,
      "ticker": "ETHB",
      "institute": "BlackRock",
      "fee": {
        "value": "0.00250000",
        "lastUpdateDate": "2026-07-02",
        "status": "1"
      },
      "netAssetsPercentage": {
        "value": "0.00237163",
        "lastUpdateDate": "2026-07-02",
        "status": "1"
      },
      "netAssets": {
        "value": "488213796.9600000000000000",
        "lastUpdateDate": "2026-07-02",
        "status": "1"
      },
      "dailyNetInflow": {
        "value": "0.0000000000000000",
        "lastUpdateDate": "2026-07-02",
        "status": "1"
      },
      "cumNetInflow": {
        "value": "518774241.3199999847000000",
        "lastUpdateDate": "2026-07-02",
        "status": "1"
      },
      "dailyValueTraded": {
        "value": "12594851.0000000000000000",
        "lastUpdateDate": "2026-07-02",
        "status": "1"
      },
      "discountPremiumRate": {
        "value": "-0.0001543885905506137",
        "lastUpdateDate": "2026-07-02",
        "status": "1"
      }
    }
  ]
}