{
  "updatedAt": "2026-06-11T08:25:49Z",
  "type": "us-btc-spot",
  "totalNetAssets": {
    "value": "77331190856.5695711000000000",
    "lastUpdateDate": "2026-06-10",
    "status": "1"
  },
  "totalNetAssetsPercentage": {
    "value": "0.06243809",
    "lastUpdateDate": "2026-06-10",
    "status": "1"
  },
  "dailyNetInflow": {
    "value": "-213849719.5000000000000000",
    "lastUpdateDate": "2026-06-10",
    "status": "1"
  },
  "cumNetInflow": {
    "value": "53557667724.113",
    "lastUpdateDate": "2026-06-10",
    "status": "1"
  },
  "dailyTotalValueTraded": {
    "value": "1901821348.0000000000000000",
    "lastUpdateDate": "2026-06-10",
    "status": "1"
  },
  "totalTokenHoldings": {
    "value": "1251335.18587935",
    "lastUpdateDate": "2026-06-10",
    "status": "1"
  },
  "list": [
    {
      "id": 1746110179689463810,
      "ticker": "IBIT",
      "institute": "BlackRock ",
      "fee": {
        "value": "0.00250000",
        "lastUpdateDate": "2026-06-10",
        "status": "1"
      },
      "netAssetsPercentage": {
        "value": "0.03811670",
        "lastUpdateDate": "2026-06-10",
        "status": "1"
      },
      "netAssets": {
        "value": "47208518720.0000100000000000",
        "lastUpdateDate": "2026-06-10",
        "status": "1"
      },
      "dailyNetInflow": {
        "value": "-148472080.0000000000000000",
        "lastUpdateDate": "2026-06-10",
        "status": "1"
      },
      "cumNetInflow": {
        "value": "62026489103.6599988825000000",
        "lastUpdateDate": "2026-06-10",
        "status": "1"
      },
      "dailyValueTraded": {
        "value": "1309848451.0000000000000000",
        "lastUpdateDate": "2026-06-10",
        "status": "1"
      },
      "discountPremiumRate": {
        "value": "0.0017991261387324542",
        "lastUpdateDate": "2026-06-10",
        "status": "1"
      }
    },
    {
      "id": 1746110179697852417,
      "ticker": "FBTC",
      "institute": "Fidelity",
      "fee": {
        "value": "0.00000000",
        "lastUpdateDate": "2026-06-10",
        "status": "1"
      },
      "netAssetsPercentage": {
        "value": "0.00897635",
        "lastUpdateDate": "2026-06-10",
        "status": "1"
      },
      "netAssets": {
        "value": "11117448102.9855600000000000",
        "lastUpdateDate": "2026-06-10",
        "status": "1"
      },
      "dailyNetInflow": {
        "value": "4039702.2750000000000000",
        "lastUpdateDate": "2026-06-10",
        "status": "1"
      },
      "cumNetInflow": {
        "value": "10435863416.7749998559000000",
        "lastUpdateDate": "2026-06-10",
        "status": "1"
      },
      "dailyValueTraded": {
        "value": "221678329.0000000000000000",
        "lastUpdateDate": "2026-06-10",
        "status": "1"
      },
      "discountPremiumRate": {
        "value": "0.0003212612988912067",
        "lastUpdateDate": "2026-06-10",
        "status": "1"
      }
    },
    {
      "id": 1746110179697852418,
      "ticker": "ARKB",
      "institute": "Ark & 21Shares",
      "fee": {
        "value": "0.00210000",
        "lastUpdateDate": "2026-06-10",
        "status": "1"
      },
      "netAssetsPercentage": {
        "value": "0.00165923",
        "lastUpdateDate": "2026-06-10",
        "status": "1"
      },
      "netAssets": {
        "value": "2054999468.7250001000000000",
        "lastUpdateDate": "2026-06-10",
        "status": "1"
      },
      "dailyNetInflow": {
        "value": "0.0000000000000000",
        "lastUpdateDate": "2026-06-10",
        "status": "1"
      },
      "cumNetInflow": {
        "value": "1271183785.3800000128000000",
        "lastUpdateDate": "2026-06-10",
        "status": "1"
      },
      "dailyValueTraded": {
        "value": "54626226.0000000000000000",
        "lastUpdateDate": "2026-06-10",
        "status": "1"
      },
      "discountPremiumRate": {
        "value": "0.0007871200453417604",
        "lastUpdateDate": "2026-06-10",
        "status": "1"
      }
    },
    {
      "id": 1746110179702046721,
      "ticker": "BTCO",
      "institute": "Invesco",
      "fee": {
        "value": "0.00250000",
        "lastUpdateDate": "2026-06-10",
        "status": "1"
      },
      "netAssetsPercentage": {
        "value": "0.00031673",
        "lastUpdateDate": "2026-06-10",
        "status": "1"
      },
      "netAssets": {
        "value": "392276766.7000000000000000",
        "lastUpdateDate": "2026-06-10",
        "status": "1"
      },
      "dailyNetInflow": {
        "value": "0.0000000000000000",
        "lastUpdateDate": "2026-06-10",
        "status": "1"
      },
      "cumNetInflow": {
        "value": "219170304.4600000081000000",
        "lastUpdateDate": "2026-06-10",
        "status": "1"
      },
      "dailyValueTraded": {
        "value": "3958029.0000000000000000",
        "lastUpdateDate": "2026-06-10",
        "status": "1"
      },
      "discountPremiumRate": {
        "value": "0.0002937226208150623",
        "lastUpdateDate": "2026-06-10",
        "status": "1"
      }
    },
    {
      "id": 1746110179706241026,
      "ticker": "BTCW",
      "institute": "WisdomTree",
      "fee": {
        "value": "0.00250000",
        "lastUpdateDate": "2026-06-10",
        "status": "1"
      },
      "netAssetsPercentage": {
        "value": "0.00011263",
        "lastUpdateDate": "2026-06-10",
        "status": "1"
      },
      "netAssets": {
        "value": "139491965.0250000000000000",
        "lastUpdateDate": "2026-06-10",
        "status": "1"
      },
      "dailyNetInflow": {
        "value": "980037.2250000000000000",
        "lastUpdateDate": "2026-06-10",
        "status": "1"
      },
      "cumNetInflow": {
        "value": "93584099.9850000046000000",
        "lastUpdateDate": "2026-06-10",
        "status": "1"
      },
      "dailyValueTraded": {
        "value": "1121827.0000000000000000",
        "lastUpdateDate": "2026-06-10",
        "status": "1"
      },
      "discountPremiumRate": {
        "value": "0.0019007033125706396",
        "lastUpdateDate": "2026-06-10",
        "status": "1"
      }
    },
    {
      "id": 1746110179706241027,
      "ticker": "BRRR",
      "institute": "Valkyrie",
      "fee": {
        "value": "0.00250000",
        "lastUpdateDate": "2026-06-10",
        "status": "1"
      },
      "netAssetsPercentage": {
        "value": "0.00029646",
        "lastUpdateDate": "2026-06-10",
        "status": "1"
      },
      "netAssets": {
        "value": "367171376.0000000000000000",
        "lastUpdateDate": "2026-06-10",
        "status": "1"
      },
      "dailyNetInflow": {
        "value": "0.0000000000000000",
        "lastUpdateDate": "2026-06-10",
        "status": "1"
      },
      "cumNetInflow": {
        "value": "312896839.4999999282000000",
        "lastUpdateDate": "2026-06-10",
        "status": "1"
      },
      "dailyValueTraded": {
        "value": "2952911.0000000000000000",
        "lastUpdateDate": "2026-06-10",
        "status": "1"
      },
      "discountPremiumRate": {
        "value": "0.0011245295575545988",
        "lastUpdateDate": "2026-06-10",
        "status": "1"
      }
    },
    {
      "id": 1746110179710435329,
      "ticker": "BITB",
      "institute": "Bitwise",
      "fee": {
        "value": "0.00200000",
        "lastUpdateDate": "2026-06-10",
        "status": "1"
      },
      "netAssetsPercentage": {
        "value": "0.00184219",
        "lastUpdateDate": "2026-06-10",
        "status": "1"
      },
      "netAssets": {
        "value": "2281594210.0900000000000000",
        "lastUpdateDate": "2026-06-10",
        "status": "1"
      },
      "dailyNetInflow": {
        "value": "0.0000000000000000",
        "lastUpdateDate": "2026-06-10",
        "status": "1"
      },
      "cumNetInflow": {
        "value": "2017811519.1999999977000000",
        "lastUpdateDate": "2026-06-10",
        "status": "1"
      },
      "dailyValueTraded": {
        "value": "61043513.0000000000000000",
        "lastUpdateDate": "2026-06-10",
        "status": "1"
      },
      "discountPremiumRate": {
        "value": "0.0015558235045922686",
        "lastUpdateDate": "2026-06-10",
        "status": "1"
      }
    },
    {
      "id": 1746110179710435330,
      "ticker": "EZBC",
      "institute": "Franklin",
      "fee": {
        "value": "0.00190000",
        "lastUpdateDate": "2026-06-10",
        "status": "1"
      },
      "netAssetsPercentage": {
        "value": "0.00028987",
        "lastUpdateDate": "2026-06-10",
        "status": "1"
      },
      "netAssets": {
        "value": "359015225.4000000000000000",
        "lastUpdateDate": "2026-06-10",
        "status": "1"
      },
      "dailyNetInflow": {
        "value": "0.0000000000000000",
        "lastUpdateDate": "2026-06-10",
        "status": "1"
      },
      "cumNetInflow": {
        "value": "335407474.0500000064000000",
        "lastUpdateDate": "2026-06-10",
        "status": "1"
      },
      "dailyValueTraded": {
        "value": "7445927.0000000000000000",
        "lastUpdateDate": "2026-06-10",
        "status": "1"
      },
      "discountPremiumRate": {
        "value": "0.001318257740943407",
        "lastUpdateDate": "2026-06-10",
        "status": "1"
      }
    },
    {
      "id": 1746110179714629633,
      "ticker": "HODL",
      "institute": "VanEck",
      "fee": {
        "value": "0.00250000",
        "lastUpdateDate": "2026-06-10",
        "status": "1"
      },
      "netAssetsPercentage": {
        "value": "0.00083452",
        "lastUpdateDate": "2026-06-10",
        "status": "1"
      },
      "netAssets": {
        "value": "1033572993.7500000000000000",
        "lastUpdateDate": "2026-06-10",
        "status": "1"
      },
      "dailyNetInflow": {
        "value": "0.0000000000000000",
        "lastUpdateDate": "2026-06-10",
        "status": "1"
      },
      "cumNetInflow": {
        "value": "1150991552.5999999665000000",
        "lastUpdateDate": "2026-06-10",
        "status": "1"
      },
      "dailyValueTraded": {
        "value": "36948116.0000000000000000",
        "lastUpdateDate": "2026-06-10",
        "status": "1"
      },
      "discountPremiumRate": {
        "value": "0.001078304344965808",
        "lastUpdateDate": "2026-06-10",
        "status": "1"
      }
    },
    {
      "id": 1746110179718823937,
      "ticker": "GBTC",
      "institute": "Grayscale",
      "fee": {
        "value": "0.01500000",
        "lastUpdateDate": "2026-06-10",
        "status": "1"
      },
      "netAssetsPercentage": {
        "value": "0.00712389",
        "lastUpdateDate": "2026-06-10",
        "status": "1"
      },
      "netAssets": {
        "value": "8823123034.0500010000000000",
        "lastUpdateDate": "2026-06-10",
        "status": "1"
      },
      "dailyNetInflow": {
        "value": "-87914115.0000000000000000",
        "lastUpdateDate": "2026-06-10",
        "status": "1"
      },
      "cumNetInflow": {
        "value": "-26851272315.0000002020000000",
        "lastUpdateDate": "2026-06-10",
        "status": "1"
      },
      "dailyValueTraded": {
        "value": "142213916.0000000000000000",
        "lastUpdateDate": "2026-06-10",
        "status": "1"
      },
      "discountPremiumRate": {
        "value": "-0.000426723285561148",
        "lastUpdateDate": "2026-06-10",
        "status": "1"
      }
    },
    {
      "id": 1746110179718823938,
      "ticker": "DEFI",
      "institute": "Hashdex",
      "fee": {
        "value": "0.00900000",
        "lastUpdateDate": "2026-06-10",
        "status": "1"
      },
      "netAssetsPercentage": {
        "value": "0.00000680",
        "lastUpdateDate": "2026-06-10",
        "status": "1"
      },
      "netAssets": {
        "value": "8424936.0000000000000000",
        "lastUpdateDate": "2026-06-10",
        "status": "1"
      },
      "dailyNetInflow": {
        "value": "0.0000000000000000",
        "lastUpdateDate": "2026-06-10",
        "status": "1"
      },
      "cumNetInflow": {
        "value": "-1448403.0000000000000000",
        "lastUpdateDate": "2026-06-10",
        "status": "1"
      },
      "dailyValueTraded": {
        "value": "4469.0000000000000000",
        "lastUpdateDate": "2026-06-10",
        "status": "1"
      },
      "discountPremiumRate": {
        "value": "0.0005198852549146427",
        "lastUpdateDate": "2026-06-10",
        "status": "1"
      }
    },
    {
      "id": 1746110179718823939,
      "ticker": "BTC",
      "institute": "Grayscale",
      "fee": {
        "value": "0.00150000",
        "lastUpdateDate": "2026-06-10",
        "status": "1"
      },
      "netAssetsPercentage": {
        "value": "0.00265892",
        "lastUpdateDate": "2026-06-10",
        "status": "1"
      },
      "netAssets": {
        "value": "3293145273.2040000000000000",
        "lastUpdateDate": "2026-06-10",
        "status": "1"
      },
      "dailyNetInflow": {
        "value": "17516736.0000000000000000",
        "lastUpdateDate": "2026-06-10",
        "status": "1"
      },
      "cumNetInflow": {
        "value": "2292638080.8879999935000000",
        "lastUpdateDate": "2026-06-10",
        "status": "1"
      },
      "dailyValueTraded": {
        "value": "53061418.0000000000000000",
        "lastUpdateDate": "2026-06-10",
        "status": "1"
      },
      "discountPremiumRate": {
        "value": "0.0003690185203453211",
        "lastUpdateDate": "2026-06-10",
        "status": "1"
      }
    },
    {
      "id": 2042438677463498754,
      "ticker": "MSBT",
      "institute": "Morgan Stanley",
      "fee": {
        "value": "0.00140000",
        "lastUpdateDate": "2026-06-10",
        "status": "1"
      },
      "netAssetsPercentage": {
        "value": "0.00020380",
        "lastUpdateDate": "2026-06-10",
        "status": "1"
      },
      "netAssets": {
        "value": "252408784.6400000000000000",
        "lastUpdateDate": "2026-06-10",
        "status": "1"
      },
      "dailyNetInflow": {
        "value": "0.0000000000000000",
        "lastUpdateDate": "2026-06-10",
        "status": "1"
      },
      "cumNetInflow": {
        "value": "272800537.9400000005000000",
        "lastUpdateDate": "2026-06-10",
        "status": "1"
      },
      "dailyValueTraded": {
        "value": "6918216.0000000000000000",
        "lastUpdateDate": "2026-06-10",
        "status": "1"
      },
      "discountPremiumRate": {
        "value": "0.0013914545822997226",
        "lastUpdateDate": "2026-06-10",
        "status": "1"
      }
    }
  ]
}